vcfViewer/__init__.py
vcfViewer/coverage.py
vcfViewer/qualplot.py
vcfViewer-0.1.dist-info/DESCRIPTION.rst
vcfViewer-0.1.dist-info/METADATA
vcfViewer-0.1.dist-info/RECORD
vcfViewer-0.1.dist-info/WHEEL
vcfViewer-0.1.dist-info/metadata.json
vcfViewer-0.1.dist-info/top_level.txt
