Metadata-Version: 2.0
Name: vcfViewer
Version: 0.1
Summary: A toolkit for visualizing VCF metadata.
Home-page: https://github.com/tomsasani/vcfViewer
Author: Tom Sasani
Author-email: tom.sasani@utah.edu
License: MIT
Platform: UNKNOWN
Classifier: Development Status :: 3 - Alpha
Classifier: License :: OSI Approved :: MIT License
Classifier: Programming Language :: Python :: 2.7
Requires-Dist: bokeh
Requires-Dist: cyvcf2
Provides-Extra: dev
Requires-Dist: check-manifest; extra == 'dev'
Provides-Extra: test
Requires-Dist: coverage; extra == 'test'
